[
  {
    "variation": "default-slice",
    "name": "Default slice",
    "slice_type": "timeline_slice",
    "items": [
      {
        "dateString": "e-enable strategic e-commerce",
        "title": "benchmark ubiquitous content",
        "subtitle": "enable revolutionary bandwidth",
        "description": "iterate proactive relationships"
      },
      {
        "dateString": "implement intuitive portals",
        "title": "incubate leading-edge infrastructures",
        "subtitle": "harness viral blockchains",
        "description": "morph dynamic infomediaries"
      },
      {
        "dateString": "disintermediate 24/7 e-markets",
        "title": "facilitate bricks-and-clicks interfaces",
        "subtitle": "engage strategic relationships",
        "description": "iterate proactive web services"
      },
      {
        "dateString": "benchmark customized e-business",
        "title": "visualize world-class functionalities",
        "subtitle": "monetize bleeding-edge vortals",
        "description": "mesh out-of-the-box synergies"
      }
    ],
    "primary": {}
  }
]